enact/__init__.py
enact/cellassign.py
enact/celltypist.py
enact/package_results.py
enact/pipeline.py
enact/assignment_methods/__init__.py
enact/assignment_methods/naive.py
enact/assignment_methods/weight_by_area.py
enact/assignment_methods/weight_by_gene.py
enact/utils/logging.py
enact_so-0.2.5.dist-info/licenses/LICENSE.md
enact_so-0.2.5.dist-info/METADATA
enact_so-0.2.5.dist-info/WHEEL
enact_so-0.2.5.dist-info/top_level.txt
enact_so-0.2.5.dist-info/RECORD
