Metadata-Version: 2.4
Name: enact-SO
Version: 0.2.5
Summary: ENACT is a self-contained pipeline designed to streamline Visium HD analysis from cell segmentation to annotation, enabling integration with advanced spatial analysis tools.
Author-email: Mena Kamel <mena.kamel@sanofi.com>, Yiwen Song <yiwen.song@sanofi.com>
License: **Copyright Sanofi 2024**
Project-URL: Documentation, https://github.com/Sanofi-Public/enact-pipeline#readme
Project-URL: Source, https://github.com/Sanofi-Public/enact-pipeline
Keywords: spatial,omics,bioinformatics,transcriptomics,VisiumHD
Classifier: Programming Language :: Python
Classifier: Programming Language :: Python :: 3.10
Classifier: Programming Language :: Python :: 3.11
Classifier: Programming Language :: Python :: 3.12
Requires-Python: >=3.9
License-File: LICENSE.md
Requires-Dist: anndata==0.10.8
Requires-Dist: fastparquet==2024.5.0
Requires-Dist: shapely==2.0.5
Requires-Dist: stardist==0.9.1
Requires-Dist: tifffile==2024.7.24
Requires-Dist: scvi-tools==1.1.6.post2
Requires-Dist: scanpy==1.10.2
Requires-Dist: geopandas==1.0.1
Requires-Dist: tensorflow==2.17.0
Requires-Dist: plotly==5.24.0
Requires-Dist: imagecodecs==2024.9.22
Requires-Dist: pyyaml==6.0
Requires-Dist: pandas
Requires-Dist: numpy
Requires-Dist: tqdm
Requires-Dist: Pillow
Requires-Dist: scipy
Requires-Dist: celltypist-SO==1.6.5
Requires-Dist: python-multipart==0.0.19
Dynamic: license-file
